[
  {
    "id": "xichu",
    "oldName": "西楚",
    "newName": "楚",
    "reason": "Trimmed suffixes/prefixes",
    "cities": [
      "徐州"
    ]
  },
  {
    "id": "weihaiwei",
    "oldName": "北洋",
    "newName": "洋",
    "reason": "Trimmed suffixes/prefixes",
    "cities": [
      "威海卫"
    ]
  },
  {
    "id": "han_d",
    "oldName": "汉",
    "newName": "汉",
    "reason": " | RULE 1 VIOLATION with city 汉中",
    "cities": [
      "汉中"
    ]
  },
  {
    "id": "qiuchi",
    "oldName": "仇池",
    "newName": "仇池",
    "reason": "Trimmed suffixes/prefixes | RULE 1 VIOLATION with city 仇池",
    "cities": [
      "仇池"
    ]
  },
  {
    "id": "dangxiang",
    "oldName": "大夏",
    "newName": "夏",
    "reason": "Trimmed suffixes/prefixes",
    "cities": [
      "兴庆府"
    ]
  },
  {
    "id": "manzhou_d",
    "oldName": "大清",
    "newName": "清",
    "reason": "Trimmed suffixes/prefixes",
    "cities": [
      "沈阳"
    ]
  },
  {
    "id": "ming_d",
    "oldName": "大明",
    "newName": "明",
    "reason": "Trimmed suffixes/prefixes",
    "cities": [
      "南京"
    ]
  },
  {
    "id": "liao_d",
    "oldName": "大辽",
    "newName": "辽",
    "reason": "Trimmed suffixes/prefixes",
    "cities": [
      "临潢府"
    ]
  },
  {
    "id": "dai_d",
    "oldName": "代",
    "newName": "代",
    "reason": " | RULE 1 VIOLATION with city 代邑",
    "cities": [
      "代邑"
    ]
  },
  {
    "id": "dayuan",
    "oldName": "大宛",
    "newName": "宛",
    "reason": "Trimmed suffixes/prefixes",
    "cities": [
      "贵山城"
    ]
  },
  {
    "id": "shache",
    "oldName": "莎车",
    "newName": "莎车",
    "reason": "Trimmed suffixes/prefixes | RULE 1 VIOLATION with city 莎车",
    "cities": [
      "莎车"
    ]
  },
  {
    "id": "yanqi",
    "oldName": "焉耆",
    "newName": "焉耆",
    "reason": "Trimmed suffixes/prefixes | RULE 1 VIOLATION with city 焉耆",
    "cities": [
      "焉耆"
    ]
  },
  {
    "id": "quanrong",
    "oldName": "犬戎",
    "newName": "犬戎",
    "reason": "Trimmed suffixes/prefixes | RULE 1 VIOLATION with city 威戎",
    "cities": [
      "威戎"
    ]
  },
  {
    "id": "yuezhi",
    "oldName": "月氏",
    "newName": "月",
    "reason": "Trimmed suffixes/prefixes",
    "cities": [
      "蓝氏城"
    ]
  },
  {
    "id": "chile",
    "oldName": "敕勒",
    "newName": "敕勒",
    "reason": "Trimmed suffixes/prefixes | RULE 1 VIOLATION with city 敕勒川",
    "cities": [
      "敕勒川"
    ]
  },
  {
    "id": "dayue",
    "oldName": "大越",
    "newName": "越",
    "reason": "Trimmed suffixes/prefixes",
    "cities": [
      "昇龙"
    ]
  },
  {
    "id": "yamato",
    "oldName": "大和",
    "newName": "和",
    "reason": "Trimmed suffixes/prefixes",
    "cities": [
      "飞鸟宫"
    ]
  },
  {
    "id": "donghu",
    "oldName": "东胡",
    "newName": "胡",
    "reason": "Trimmed suffixes/prefixes",
    "cities": [
      "徒河"
    ]
  },
  {
    "id": "linyi",
    "oldName": "林邑",
    "newName": "林邑",
    "reason": "Trimmed suffixes/prefixes | RULE 1 VIOLATION with city 象林",
    "cities": [
      "象林"
    ]
  },
  {
    "id": "xu",
    "oldName": "徐",
    "newName": "徐",
    "reason": " | RULE 1 VIOLATION with city 徐城",
    "cities": [
      "徐城"
    ]
  },
  {
    "id": "baibo",
    "oldName": "白波",
    "newName": "白波",
    "reason": "Trimmed suffixes/prefixes | RULE 1 VIOLATION with city 白波谷",
    "cities": [
      "白波谷"
    ]
  },
  {
    "id": "xiqin",
    "oldName": "西秦",
    "newName": "秦",
    "reason": "Trimmed suffixes/prefixes",
    "cities": [
      "兰州"
    ]
  },
  {
    "id": "nanzhao",
    "oldName": "南诏",
    "newName": "诏",
    "reason": "Trimmed suffixes/prefixes",
    "cities": [
      "蒙舍城"
    ]
  },
  {
    "id": "dashi",
    "oldName": "大食",
    "newName": "食",
    "reason": "Trimmed suffixes/prefixes",
    "cities": []
  },
  {
    "id": "dongdan",
    "oldName": "东丹",
    "newName": "丹",
    "reason": "Trimmed suffixes/prefixes",
    "cities": [
      "卑沙城"
    ]
  },
  {
    "id": "dali",
    "oldName": "大理",
    "newName": "理",
    "reason": "Trimmed suffixes/prefixes",
    "cities": [
      "羊苴咩城"
    ]
  },
  {
    "id": "nongzhigao",
    "oldName": "大南",
    "newName": "南",
    "reason": "Trimmed suffixes/prefixes",
    "cities": [
      "邕州"
    ]
  },
  {
    "id": "pagan",
    "oldName": "蒲甘",
    "newName": "蒲甘",
    "reason": "Trimmed suffixes/prefixes | RULE 1 VIOLATION with city 蒲甘",
    "cities": [
      "蒲甘"
    ]
  },
  {
    "id": "dongxia",
    "oldName": "东夏",
    "newName": "夏",
    "reason": "Trimmed suffixes/prefixes",
    "cities": [
      "敖东城"
    ]
  },
  {
    "id": "zhangshicheng",
    "oldName": "大周",
    "newName": "周",
    "reason": "Trimmed suffixes/prefixes",
    "cities": [
      "常州"
    ]
  },
  {
    "id": "daxing",
    "oldName": "大兴",
    "newName": "兴",
    "reason": "Trimmed suffixes/prefixes",
    "cities": [
      "宁海"
    ]
  },
  {
    "id": "fang_guozhen",
    "oldName": "方国",
    "newName": "方",
    "reason": "Trimmed suffixes/prefixes",
    "cities": [
      "庆元"
    ]
  },
  {
    "id": "yeren_nvzhen",
    "oldName": "野人",
    "newName": "野",
    "reason": "Trimmed suffixes/prefixes",
    "cities": [
      "黑龙江城"
    ]
  },
  {
    "id": "chijin",
    "oldName": "赤斤",
    "newName": "赤斤",
    "reason": "Trimmed suffixes/prefixes | RULE 1 VIOLATION with city 赤金堡",
    "cities": [
      "赤金堡"
    ]
  },
  {
    "id": "anding_wei",
    "oldName": "安定",
    "newName": "安定",
    "reason": "Trimmed suffixes/prefixes | RULE 1 VIOLATION with city 安定卫",
    "cities": [
      "安定卫"
    ]
  },
  {
    "id": "joseon",
    "oldName": "朝鲜",
    "newName": "鲜",
    "reason": "Trimmed suffixes/prefixes",
    "cities": [
      "平壤"
    ]
  },
  {
    "id": "dahan",
    "oldName": "大韩",
    "newName": "韩",
    "reason": "Trimmed suffixes/prefixes",
    "cities": [
      "汉城"
    ]
  },
  {
    "id": "dashun",
    "oldName": "大顺",
    "newName": "顺",
    "reason": "Trimmed suffixes/prefixes",
    "cities": [
      "渭南"
    ]
  },
  {
    "id": "daxi_ming",
    "oldName": "大西",
    "newName": "西",
    "reason": "Trimmed suffixes/prefixes",
    "cities": [
      "涪城"
    ]
  },
  {
    "id": "dzungar",
    "oldName": "准噶尔",
    "newName": "准噶尔",
    "reason": "Trimmed suffixes/prefixes | RULE 1 VIOLATION with city 伊犁固尔札",
    "cities": [
      "伊犁固尔札"
    ]
  },
  {
    "id": "yarkand",
    "oldName": "叶尔羌",
    "newName": "叶尔羌",
    "reason": "Trimmed suffixes/prefixes | RULE 1 VIOLATION with city 英吉沙尔",
    "cities": [
      "英吉沙尔"
    ]
  },
  {
    "id": "kokand",
    "oldName": "霍罕",
    "newName": "霍罕",
    "reason": "Trimmed suffixes/prefixes | RULE 1 VIOLATION with city 浩罕",
    "cities": [
      "浩罕"
    ]
  },
  {
    "id": "dacheng",
    "oldName": "大成",
    "newName": "成",
    "reason": "Trimmed suffixes/prefixes",
    "cities": [
      "永安"
    ]
  },
  {
    "id": "daming",
    "oldName": "大明国",
    "newName": "明",
    "reason": "Trimmed suffixes/prefixes",
    "cities": []
  },
  {
    "id": "han_nian",
    "oldName": "大汉",
    "newName": "汉",
    "reason": "Trimmed suffixes/prefixes",
    "cities": [
      "雉河集"
    ]
  },
  {
    "id": "han_dadian",
    "oldName": "大汉捻",
    "newName": "汉捻",
    "reason": "Trimmed suffixes/prefixes",
    "cities": [
      "洋县"
    ]
  },
  {
    "id": "qianhui",
    "oldName": "回军",
    "newName": "回",
    "reason": "Trimmed suffixes/prefixes",
    "cities": [
      "偏刀水"
    ]
  },
  {
    "id": "miao_qing",
    "oldName": "苗军",
    "newName": "苗",
    "reason": "Trimmed suffixes/prefixes",
    "cities": [
      "且兰城"
    ]
  },
  {
    "id": "dajin",
    "oldName": "大金",
    "newName": "金",
    "reason": "Trimmed suffixes/prefixes",
    "cities": [
      "会宁府"
    ]
  },
  {
    "id": "yuan_d",
    "oldName": "大元",
    "newName": "元",
    "reason": "Trimmed suffixes/prefixes",
    "cities": [
      "上都"
    ]
  },
  {
    "id": "tunggiya",
    "oldName": "佟佳",
    "newName": "佟佳",
    "reason": "Trimmed suffixes/prefixes | RULE 1 VIOLATION with city 佟佳江",
    "cities": [
      "佟佳江"
    ]
  },
  {
    "id": "kangju",
    "oldName": "康居",
    "newName": "康居",
    "reason": "Trimmed suffixes/prefixes | RULE 1 VIOLATION with city 康卡",
    "cities": [
      "康卡"
    ]
  },
  {
    "id": "da_yuan",
    "oldName": "北元",
    "newName": "元",
    "reason": "Trimmed suffixes/prefixes",
    "cities": [
      "应昌"
    ]
  },
  {
    "id": "tsangpa",
    "oldName": "藏巴汗",
    "newName": "藏巴",
    "reason": "Trimmed suffixes/prefixes",
    "cities": [
      "桑珠孜"
    ]
  },
  {
    "id": "bailan",
    "oldName": "白兰",
    "newName": "白兰",
    "reason": "Trimmed suffixes/prefixes | RULE 1 VIOLATION with city 白海堡",
    "cities": [
      "白海堡"
    ]
  },
  {
    "id": "ava",
    "oldName": "阿瓦",
    "newName": "阿瓦",
    "reason": "Trimmed suffixes/prefixes | RULE 1 VIOLATION with city 阿瓦",
    "cities": [
      "阿瓦"
    ]
  },
  {
    "id": "dongxu",
    "oldName": "东吁",
    "newName": "吁",
    "reason": "Trimmed suffixes/prefixes",
    "cities": [
      "勃固城"
    ]
  },
  {
    "id": "nanyue",
    "oldName": "南越",
    "newName": "越",
    "reason": "Trimmed suffixes/prefixes",
    "cities": [
      "横浦关"
    ]
  },
  {
    "id": "nanhan",
    "oldName": "南汉",
    "newName": "汉",
    "reason": "Trimmed suffixes/prefixes",
    "cities": [
      "湟溪关"
    ]
  },
  {
    "id": "xiou",
    "oldName": "西瓯",
    "newName": "瓯",
    "reason": "Trimmed suffixes/prefixes",
    "cities": [
      "布山"
    ]
  },
  {
    "id": "weili",
    "oldName": "尉犁",
    "newName": "尉犁",
    "reason": "Trimmed suffixes/prefixes | RULE 1 VIOLATION with city 尉犁",
    "cities": [
      "尉犁"
    ]
  },
  {
    "id": "juandu",
    "oldName": "捐毒",
    "newName": "捐毒",
    "reason": "Trimmed suffixes/prefixes | RULE 1 VIOLATION with city 捐毒",
    "cities": [
      "捐毒"
    ]
  },
  {
    "id": "pishan",
    "oldName": "皮山",
    "newName": "皮山",
    "reason": "Trimmed suffixes/prefixes | RULE 1 VIOLATION with city 皮山",
    "cities": [
      "皮山"
    ]
  },
  {
    "id": "seljuq",
    "oldName": "塞尔柱",
    "newName": "塞尔柱",
    "reason": "Trimmed suffixes/prefixes | RULE 1 VIOLATION with city 梅尔夫",
    "cities": [
      "梅尔夫"
    ]
  },
  {
    "id": "yong",
    "oldName": "庸",
    "newName": "庸",
    "reason": " | RULE 1 VIOLATION with city 上庸",
    "cities": [
      "上庸"
    ]
  },
  {
    "id": "hepan",
    "oldName": "喝槃陀",
    "newName": "喝槃陀",
    "reason": "Trimmed suffixes/prefixes | RULE 1 VIOLATION with city 喝槃陀城",
    "cities": [
      "喝槃陀城"
    ]
  },
  {
    "id": "humi",
    "oldName": "护密",
    "newName": "护密",
    "reason": "Trimmed suffixes/prefixes | RULE 1 VIOLATION with city 护密城",
    "cities": [
      "护密城",
      "昏度多"
    ]
  },
  {
    "id": "heishui",
    "oldName": "黑水",
    "newName": "黑水",
    "reason": "Trimmed suffixes/prefixes | RULE 1 VIOLATION with city 黑水塞",
    "cities": [
      "黑水塞"
    ]
  },
  {
    "id": "nanjie",
    "oldName": "南杰",
    "newName": "杰",
    "reason": "Trimmed suffixes/prefixes",
    "cities": [
      "日土宗"
    ]
  },
  {
    "id": "dawoer",
    "oldName": "达斡尔",
    "newName": "达斡尔",
    "reason": "Trimmed suffixes/prefixes | RULE 1 VIOLATION with city 莫尔根",
    "cities": [
      "莫尔根"
    ]
  },
  {
    "id": "guangnanguo",
    "oldName": "广南国",
    "newName": "广南",
    "reason": "Trimmed suffixes/prefixes",
    "cities": [
      "洞海城"
    ]
  },
  {
    "id": "liren",
    "oldName": "俚人",
    "newName": "俚",
    "reason": "Trimmed suffixes/prefixes",
    "cities": [
      "珠崖总峒"
    ]
  },
  {
    "id": "dayu",
    "oldName": "大隅",
    "newName": "隅",
    "reason": "Trimmed suffixes/prefixes",
    "cities": [
      "赤尾木城"
    ]
  },
  {
    "id": "gar_kham",
    "oldName": "德格",
    "newName": "德格",
    "reason": "Trimmed suffixes/prefixes | RULE 1 VIOLATION with city 德格",
    "cities": [
      "德格"
    ]
  },
  {
    "id": "houtu",
    "oldName": "后突",
    "newName": "突",
    "reason": "Trimmed suffixes/prefixes",
    "cities": []
  },
  {
    "id": "keerkezi",
    "oldName": "柯尔克孜",
    "newName": "柯尔克孜",
    "reason": "Trimmed suffixes/prefixes | RULE 1 VIOLATION with city 伊尔克什坦",
    "cities": [
      "伊尔克什坦"
    ]
  },
  {
    "id": "weiru",
    "oldName": "卫茹",
    "newName": "茹",
    "reason": "Trimmed suffixes/prefixes",
    "cities": []
  },
  {
    "id": "liguo",
    "oldName": "黎国",
    "newName": "黎",
    "reason": "Trimmed suffixes/prefixes",
    "cities": [
      "阏与"
    ]
  },
  {
    "id": "lishi",
    "oldName": "李氏",
    "newName": "李",
    "reason": "Trimmed suffixes/prefixes",
    "cities": [
      "襄武"
    ]
  },
  {
    "id": "kaerka",
    "oldName": "喀尔喀",
    "newName": "喀尔喀",
    "reason": "Trimmed suffixes/prefixes | RULE 1 VIOLATION with city 特尔浑军台",
    "cities": [
      "特尔浑军台"
    ]
  },
  {
    "id": "wuzhumuqin",
    "oldName": "乌珠穆沁",
    "newName": "乌珠穆沁",
    "reason": "Trimmed suffixes/prefixes | RULE 1 VIOLATION with city 巴彦乌拉",
    "cities": [
      "巴彦乌拉",
      "乌里雅斯太"
    ]
  },
  {
    "id": "panjun",
    "oldName": "叛军",
    "newName": "叛",
    "reason": "Trimmed suffixes/prefixes",
    "cities": [
      "泾州",
      "果州",
      "资州",
      "景州",
      "街亭",
      "陇州",
      "松州",
      "朐城",
      "大散关",
      "独松关",
      "仙霞关",
      "剑门关",
      "子午谷",
      "鹿头关",
      "函谷关",
      "潼关",
      "广成关",
      "偏头关",
      "平型关",
      "灵石关",
      "金锁关",
      "轵关",
      "井陉关",
      "倒马关",
      "飞狐",
      "紫荆关",
      "武胜关",
      "穆陵关",
      "青石关",
      "钓鱼城",
      "迭州",
      "潘州",
      "茂州",
      "永宁",
      "高阙塞",
      "阳山关",
      "东胜州",
      "隆桥驿",
      "淮阴",
      "当阳",
      "婼羌",
      "且末",
      "星星峡",
      "玉门关",
      "阳关",
      "武州塞",
      "鸡鹿塞",
      "固阳塞",
      "夏阳渡",
      "漂渝津",
      "天井关",
      "咸兴",
      "海州",
      "瞿塘关",
      "燕然山",
      "狼居胥山",
      "燕然勒石",
      "涿邪山",
      "孽多城",
      "金山",
      "福海",
      "汀州",
      "武定州",
      "穹窿银城",
      "乌蒙山",
      "宁武关",
      "庆州",
      "石门关",
      "古严关",
      "麦岭关",
      "大斗拔谷",
      "三陇沙",
      "肩水金关",
      "博尔巴任",
      "独逻河",
      "赛尔乌苏",
      "布尔根军台",
      "息城",
      "忽毡",
      "昆岗",
      "龙木错",
      "多玛",
      "普兰",
      "大通",
      "赛音山达",
      "尉头城"
    ]
  },
  {
    "id": "yutian",
    "oldName": "于阗",
    "newName": "于阗",
    "reason": "Trimmed suffixes/prefixes | RULE 1 VIOLATION with city 于阗",
    "cities": [
      "于阗"
    ]
  },
  {
    "id": "yumi",
    "oldName": "扜弥",
    "newName": "扜弥",
    "reason": "Trimmed suffixes/prefixes | RULE 1 VIOLATION with city 扜弥",
    "cities": [
      "扜弥"
    ]
  },
  {
    "id": "xiye",
    "oldName": "西夜",
    "newName": "夜",
    "reason": "Trimmed suffixes/prefixes",
    "cities": [
      "克里雅山口"
    ]
  },
  {
    "id": "galangdiba",
    "oldName": "噶朗第巴",
    "newName": "噶朗第巴",
    "reason": "Trimmed suffixes/prefixes | RULE 1 VIOLATION with city 噶朗宗",
    "cities": [
      "噶朗宗"
    ]
  },
  {
    "id": "qiong",
    "oldName": "邛",
    "newName": "邛",
    "reason": " | RULE 1 VIOLATION with city 邛都",
    "cities": [
      "邛都"
    ]
  },
  {
    "id": "zhuoshi",
    "oldName": "卓氏",
    "newName": "卓",
    "reason": "Trimmed suffixes/prefixes",
    "cities": [
      "临邛"
    ]
  },
  {
    "id": "pengshi",
    "oldName": "彭氏",
    "newName": "彭",
    "reason": "Trimmed suffixes/prefixes",
    "cities": [
      "辰州"
    ]
  },
  {
    "id": "cuanshi",
    "oldName": "爨氏",
    "newName": "爨",
    "reason": "Trimmed suffixes/prefixes",
    "cities": [
      "味县"
    ]
  },
  {
    "id": "dianguo",
    "oldName": "滇国",
    "newName": "滇",
    "reason": "Trimmed suffixes/prefixes",
    "cities": [
      "拓东城"
    ]
  },
  {
    "id": "nanqiao",
    "oldName": "南谯",
    "newName": "谯",
    "reason": "Trimmed suffixes/prefixes",
    "cities": [
      "清流关"
    ]
  },
  {
    "id": "cai",
    "oldName": "蔡",
    "newName": "蔡",
    "reason": " | RULE 1 VIOLATION with city 新蔡",
    "cities": [
      "新蔡"
    ]
  },
  {
    "id": "boren",
    "oldName": "僰人",
    "newName": "僰",
    "reason": "Trimmed suffixes/prefixes | RULE 1 VIOLATION with city 僰道",
    "cities": [
      "僰道"
    ]
  },
  {
    "id": "qi2",
    "oldName": "蕲",
    "newName": "蕲",
    "reason": " | RULE 1 VIOLATION with city 蕲春",
    "cities": [
      "蕲春"
    ]
  },
  {
    "id": "houliao",
    "oldName": "后辽",
    "newName": "辽",
    "reason": "Trimmed suffixes/prefixes",
    "cities": [
      "咸平"
    ]
  },
  {
    "id": "dazhen",
    "oldName": "大真",
    "newName": "真",
    "reason": "Trimmed suffixes/prefixes",
    "cities": [
      "恤品"
    ]
  },
  {
    "id": "dayuzi",
    "oldName": "大玉兹",
    "newName": "玉兹",
    "reason": "Trimmed suffixes/prefixes",
    "cities": [
      "塞兰"
    ]
  },
  {
    "id": "weiwuer",
    "oldName": "维吾尔",
    "newName": "维吾尔",
    "reason": "Trimmed suffixes/prefixes | RULE 1 VIOLATION with city 玉尔滚",
    "cities": [
      "玉尔滚"
    ]
  },
  {
    "id": "keerqin",
    "oldName": "科尔沁",
    "newName": "科尔沁",
    "reason": "Trimmed suffixes/prefixes | RULE 1 VIOLATION with city 达尔罕",
    "cities": [
      "达尔罕"
    ]
  }
]